image-encoder/__init__.py
image-encoder/image_encoder.py
image_encoder/__init__.py
image_encoder/image_encoder.py
image_encoder-0.0.8.dist-info/LICENSE
image_encoder-0.0.8.dist-info/METADATA
image_encoder-0.0.8.dist-info/WHEEL
image_encoder-0.0.8.dist-info/top_level.txt
image_encoder-0.0.8.dist-info/RECORD
