Metadata-Version: 2.1
Name: image-encoder
Version: 0.0.8
Summary: A simple way to encode and decode images for REST calls
Home-page: https://github.com/jagath-jaikumar/image-encoder
Author: Jagath Jai Kumar
Author-email: jagath.jaikumar@gmail.com
License: UNKNOWN
Platform: UNKNOWN
Classifier: Programming Language :: Python :: 3
Classifier: License :: OSI Approved :: MIT License
Classifier: Operating System :: OS Independent
Requires-Python: >=3.6
Requires-Dist: Pillow (>=6.2.0)
